MANIFEST.in
README.md
setup.py
linkurious_component/__init__.py
linkurious_component/bundle.js
linkurious_component/metadata.json
linkurious_component/version.py
linkurious_component.egg-info/PKG-INFO
linkurious_component.egg-info/SOURCES.txt
linkurious_component.egg-info/dependency_links.txt
linkurious_component.egg-info/top_level.txt