Metadata-Version: 1.0
Name: linkurious-component
Version: 0.0.1
Summary: Component to load the data from linkurious lib
Home-page: UNKNOWN
Author: iamrajhans
Author-email: UNKNOWN
License: MIT
Platform: UNKNOWN
